{"cameraMode":{"drawMode":0,"name":"Shaded","section":"Shading Mode"},"sceneLighting":false,"audioPlay":false,"sceneViewState":{"m_AlwaysRefresh":false,"showFog":true,"showSkybox":false,"showFlares":true,"showImageEffects":true,"showParticleSystems":true,"showVisualEffectGraphs":true,"m_FxEnabled":true},"in2DMode":false,"pivot":{"x":-0.3705058991909027,"y":2.1707828044891359,"z":0.42503437399864199},"rotation":{"x":-0.034885093569755557,"y":-0.7103061676025391,"z":0.03553314507007599,"w":-0.7022975087165833},"size":1.9700301885604859,"orthographic":false}